LICENSE.txt
MANIFEST.in
README.md
requirements.txt
setup.py
django_fastbill/__init__.py
django_fastbill/admin.py
django_fastbill/exceptions.py
django_fastbill/helper.py
django_fastbill/managers.py
django_fastbill/models.py
django_fastbill/notifications.py
django_fastbill/signals.py
django_fastbill/tasks.py
django_fastbill/tests.py
django_fastbill/urls.py
django_fastbill/views.py
django_fastbill.egg-info/PKG-INFO
django_fastbill.egg-info/SOURCES.txt
django_fastbill.egg-info/dependency_links.txt
django_fastbill.egg-info/requires.txt
django_fastbill.egg-info/top_level.txt
django_fastbill/management/.DS_Store
django_fastbill/management/__init__.py
django_fastbill/management/commands/__init__.py
django_fastbill/management/commands/fastbill.py
django_fastbill/migrations/0001_initial.py
django_fastbill/migrations/0002_auto__del_field_invoice_invoice_ttitle__add_field_invoice_invoice_titl.py
django_fastbill/migrations/0003_auto__del_field_subscription_fastbill_customer__del_field_subscription.py
django_fastbill/migrations/0004_auto__add_field_customer_deleted.py
django_fastbill/migrations/0005_auto__chg_field_invoice_affiliate.py
django_fastbill/migrations/__init__.py
django_fastbill/templates/.DS_Store
django_fastbill/templates/django_fastbill/checkout_error.html
django_fastbill/templates/django_fastbill/order.html
django_fastbill/templates/django_fastbill/user.html