Metadata-Version: 1.0
Name: django-fastbill
Version: 0.2.6
Summary: A thin python wrapper for the fastbill API
Home-page: http://github.com/jayfk/django-fastbill
Author: Jannis Gebauer
Author-email: ja.geb@pricemesh.io
License: MIT License
Keywords: fastbill api
Platform: UNKNOWN
